abcdef_test_ti_client/__init__.py
abcdef_test_ti_client/api_client.py
abcdef_test_ti_client/api_response.py
abcdef_test_ti_client/configuration.py
abcdef_test_ti_client/exceptions.py
abcdef_test_ti_client/py.typed
abcdef_test_ti_client/rest.py
abcdef_test_ti_client/api/__init__.py
abcdef_test_ti_client/api/pet_api.py
abcdef_test_ti_client/api/store_api.py
abcdef_test_ti_client/api/user_api.py
abcdef_test_ti_client/models/__init__.py
abcdef_test_ti_client/models/address.py
abcdef_test_ti_client/models/api_response.py
abcdef_test_ti_client/models/category.py
abcdef_test_ti_client/models/customer.py
abcdef_test_ti_client/models/order.py
abcdef_test_ti_client/models/pet.py
abcdef_test_ti_client/models/tag.py
abcdef_test_ti_client/models/user.py
abcdef_test_ti_client-1.0.0.dist-info/METADATA
abcdef_test_ti_client-1.0.0.dist-info/WHEEL
abcdef_test_ti_client-1.0.0.dist-info/top_level.txt
abcdef_test_ti_client-1.0.0.dist-info/RECORD
